touchtype/__init__.py
touchtype/colors.py
touchtype/layouts.py
touchtype/levels.py
touchtype/tutorial.py
touchtype-0.0.1.dist-info/LICENSE
touchtype-0.0.1.dist-info/METADATA
touchtype-0.0.1.dist-info/WHEEL
touchtype-0.0.1.dist-info/entry_points.txt
touchtype-0.0.1.dist-info/top_level.txt
touchtype-0.0.1.dist-info/RECORD
