Metadata-Version: 2.1
Name: touchtype
Version: 0.0.1
Summary: A command line application for practising typing on a keyboard.
Author-email: Nico Mellon <nmellon94@gmail.com>
Project-URL: Homepage, https://github.com/nicomellon/touchtype
Project-URL: Bug Tracker, https://github.com/nicomellon/touchtype/issues
Classifier: Programming Language :: Python :: 3
Classifier: License :: OSI Approved :: MIT License
Classifier: Operating System :: OS Independent
Requires-Python: >=3.7
License-File: LICENSE
